oslo_metrics/__init__.py
oslo_metrics/__main__.py
oslo_metrics/message_router.py
oslo_metrics/message_type.py
oslo_metrics/metrics/__init__.py
oslo_metrics/metrics/oslo_messaging.py
oslo_metrics/tests/__init__.py
oslo_metrics/tests/test_message_process.py
oslo_metrics/tests/test_message_validation.py
oslo_metrics-0.14.0.dist-info/AUTHORS
oslo_metrics-0.14.0.dist-info/LICENSE
oslo_metrics-0.14.0.dist-info/METADATA
oslo_metrics-0.14.0.dist-info/WHEEL
oslo_metrics-0.14.0.dist-info/entry_points.txt
oslo_metrics-0.14.0.dist-info/pbr.json
oslo_metrics-0.14.0.dist-info/top_level.txt
oslo_metrics-0.14.0.dist-info/RECORD
