Metadata-Version: 2.1
Name: oslo.metrics
Version: 0.14.0
Summary: Oslo Metrics API
Home-page: https://opendev.org/openstack/oslo.metrics
Author: OpenStack
Author-email: openstack-discuss@lists.openstack.org
Classifier: Environment :: OpenStack
Classifier: Intended Audience :: Developers
Classifier: Intended Audience :: Information Technology
Classifier: License :: OSI Approved :: Apache Software License
Classifier: Operating System :: OS Independent
Classifier: Programming Language :: Python
Classifier: Programming Language :: Python :: 3
Classifier: Programming Language :: Python :: 3.10
Classifier: Programming Language :: Python :: 3.11
Classifier: Programming Language :: Python :: 3.12
Classifier: Programming Language :: Python :: 3.13
Classifier: Programming Language :: Python :: 3 :: Only
Classifier: Programming Language :: Python :: Implementation :: CPython
Requires-Python: >=3.10
License-File: LICENSE
Requires-Dist: pbr>=3.1.1
Requires-Dist: oslo.utils>=3.41.0
Requires-Dist: oslo.log>=3.44.0
Requires-Dist: oslo.config>=6.9.0
Requires-Dist: prometheus-client>=0.6.0
